OpenApiDriver/__init__.py
OpenApiDriver/openapi_executors.py
OpenApiDriver/openapi_reader.py
OpenApiDriver/openapidriver.libspec
OpenApiDriver/openapidriver.py
OpenApiDriver/py.typed
OpenApiLibCore/__init__.py
OpenApiLibCore/annotations.py
OpenApiLibCore/data_generation/__init__.py
OpenApiLibCore/data_generation/body_data_generation.py
OpenApiLibCore/data_generation/data_generation_core.py
OpenApiLibCore/data_invalidation.py
OpenApiLibCore/dto_base.py
OpenApiLibCore/dto_utils.py
OpenApiLibCore/localized_faker.py
OpenApiLibCore/models.py
OpenApiLibCore/oas_cache.py
OpenApiLibCore/openapi_libcore.libspec
OpenApiLibCore/openapi_libcore.py
OpenApiLibCore/parameter_utils.py
OpenApiLibCore/path_functions.py
OpenApiLibCore/path_invalidation.py
OpenApiLibCore/protocols.py
OpenApiLibCore/py.typed
OpenApiLibCore/request_data.py
OpenApiLibCore/resource_relations.py
OpenApiLibCore/validation.py
OpenApiLibCore/value_utils.py
openapi_libgen/__init__.py
openapi_libgen/command_line.py
openapi_libgen/generator.py
openapi_libgen/parsing_utils.py
openapi_libgen/spec_parser.py
openapi_libgen/templates/__init__.jinja
openapi_libgen/templates/library.jinja
openapitools_docs/__init__.py
openapitools_docs/docstrings.py
openapitools_docs/documentation_generator.py
openapitools_docs/templates/documentation.jinja
robotframework_openapitools-1.0.5.dist-info/LICENSE
robotframework_openapitools-1.0.5.dist-info/METADATA
robotframework_openapitools-1.0.5.dist-info/WHEEL
robotframework_openapitools-1.0.5.dist-info/entry_points.txt
robotframework_openapitools-1.0.5.dist-info/RECORD
