Metadata-Version: 2.3
Name: robotframework-openapitools
Version: 1.0.5
Summary: A set of Robot Framework libraries to test APIs for which the OAS is available.
License: Apache License
Author: Robin Mackaij
Author-email: r.a.mackaij@gmail.com
Maintainer: Robin Mackaij
Maintainer-email: r.a.mackaij@gmail.com
Requires-Python: >=3.10, <4
Classifier: Programming Language :: Python :: 3
Classifier: Programming Language :: Python :: 3.10
Classifier: Programming Language :: Python :: 3.11
Classifier: Programming Language :: Python :: 3.12
Classifier: Programming Language :: Python :: 3.13
Classifier: Programming Language :: Python :: 3.14
Classifier: License :: OSI Approved :: Apache Software License
Classifier: Operating System :: OS Independent
Classifier: Topic :: Software Development :: Testing
Classifier: Topic :: Software Development :: Testing :: Acceptance
Classifier: Framework :: Robot Framework
Requires-Dist: Faker (>=23.1.0)
Requires-Dist: Jinja2 (>=3.1.2)
Requires-Dist: black (>=24.1.0)
Requires-Dist: openapi-core (>=0.19.0)
Requires-Dist: prance[cli] (>=23)
Requires-Dist: pydantic (>=2.11.0)
Requires-Dist: requests (>=2.31.0)
Requires-Dist: rich_click (>=1.7.0)
Requires-Dist: robotframework (>=6.0.0,!=7.0.0)
Requires-Dist: robotframework-datadriver (>=1.10.0)
Requires-Dist: rstr (>=3.2.0)
Project-URL: Documentation, https://marketsquare.github.io/robotframework-openapitools
Project-URL: Homepage, https://github.com/MarketSquare/robotframework-openapitools
Project-URL: Repository, https://github.com/MarketSquare/robotframework-openapitools.git
